bocks_ds/__init__.py
bocks_ds/client.py
bocks_ds/errors.py
bocks_ds/fields.py
datasource_python/__init__.py
datasource_python/client.py
datasource_python/errors.py
bocks_ds-0.2.1.dist-info/LICENSE
bocks_ds-0.2.1.dist-info/METADATA
bocks_ds-0.2.1.dist-info/WHEEL
bocks_ds-0.2.1.dist-info/top_level.txt
bocks_ds-0.2.1.dist-info/RECORD
