Metadata-Version: 2.1
Name: bocks-ds
Version: 0.2.1
Summary: DataSource Python SDK
Home-page: https://github.com/bocks-ds/datasource-python
Author: Bocks
License: UNKNOWN
Platform: UNKNOWN
Classifier: Development Status :: 3 - Alpha
Classifier: Programming Language :: Python :: 3
Classifier: License :: OSI Approved :: GNU General Public License v3 (GPLv3)
Classifier: License :: Free for non-commercial use
Classifier: Operating System :: OS Independent
Requires-Python: >=3.6
Requires-Dist: pycurl
